py4geo/__init__.py
py4geo/common.py
py4geo/models.py
py4geo/settings.py
py4geo/client/__init__.py
py4geo/client/common.py
py4geo/client/models.py
py4geo/client/queryhelper.py
py4geo/client/table.py
py4geo/client/controllers/__init__.py
py4geo/client/controllers/tools.py
py4geo/client/controllers/advanced/__init__.py
py4geo/client/controllers/advanced/callbacks.py
py4geo/client/controllers/advanced/common.py
py4geo/client/controllers/base/__init__.py
py4geo/client/controllers/base/callbacks.py
py4geo/populate/__init__.py
py4geo/populate/base.py
py4geo/populate/gjson.py
py4geo/populate/io.py
py4geo/populate/models.py
py4geo/populate/osm.py
py4geo/populate/pgcopy.py
py4geo/populate/test.py
py4geo/populate/tools.py
py4geo/populate/optutils/__init__.py
py4geo/populate/optutils/base.py
py4geo/populate/optutils/geom.py
py4geo/populate/optutils/tools.py
py4geo/setup/__init__.py
py4geo/setup/models.py
py4geo/setup/pgfunctions.py
py4geo/setup/pgviews.py
py4geo/setup/setup.py
py4geo/setup/sql/__init__.py
py4geo/setup/sql/geoviews.py
py4geo/setup/sql/mercantile.sql
py4geo/tools/__init__.py
py4geo/tools/tile.py
py4geo/tools/tilesets.py
py4geo-1.0.8.dist-info/LICENCE
py4geo-1.0.8.dist-info/METADATA
py4geo-1.0.8.dist-info/WHEEL
py4geo-1.0.8.dist-info/top_level.txt
py4geo-1.0.8.dist-info/RECORD
