Metadata-Version: 2.1
Name: py4geo
Version: 1.0.8
Summary: My geo package
Home-page: https://github.com/manuelep/py4geo
Author: Manuele Pesenti
Author-email: manuele@inventati.org
License: UNKNOWN
Project-URL: Bug Tracker, https://github.com/manuelep/py4geo/issues
Platform: UNKNOWN
Classifier: Programming Language :: Python :: 3
Classifier: License :: OSI Approved :: Apache Software License
Classifier: Operating System :: OS Independent
Requires-Python: >=3.6
License-File: LICENCE
Requires-Dist: overpy
Requires-Dist: shapely
Requires-Dist: ujson
Requires-Dist: pyproj
Requires-Dist: mercantile
Requires-Dist: lxml
Requires-Dist: geojson
Requires-Dist: hashids
Requires-Dist: tqdm
Requires-Dist: geomet
Requires-Dist: h3
Requires-Dist: mptools (>=1.0.7)
Requires-Dist: py4vtile
Requires-Dist: supermercado
Requires-Dist: osm2geojson
